wattrex_battery_cycler_cu_manager/__init__.py
wattrex_battery_cycler_cu_manager/__version__.py
wattrex_battery_cycler_cu_manager/cu_broker_client.py
wattrex_battery_cycler_cu_manager/cu_manager.py
wattrex_battery_cycler_cu_manager/detect.py
wattrex_battery_cycler_cu_manager/register.py
wattrex_battery_cycler_cu_manager-0.0.2.dist-info/LICENSE.txt
wattrex_battery_cycler_cu_manager-0.0.2.dist-info/METADATA
wattrex_battery_cycler_cu_manager-0.0.2.dist-info/WHEEL
wattrex_battery_cycler_cu_manager-0.0.2.dist-info/top_level.txt
wattrex_battery_cycler_cu_manager-0.0.2.dist-info/RECORD
